{
  "" : {
    "transaction" : "",
    "sampleCount" : 10000,
    "errorCount" : 2593,
    "errorPct" : 25.93,
    "meanResTime" : 7439.395999999995,
    "medianResTime" : 5150.5,
    "minResTime" : 44.0,
    "maxResTime" : 64281.0,
    "pct1ResTime" : 16558.799999999996,
    "pct2ResTime" : 21467.59999999997,
    "pct3ResTime" : 30389.0,
    "throughput" : 22.754837109498553,
    "receivedKBytesPerSec" : 2386.139157188566,
    "sentKBytesPerSec" : 70.34444565803575
  },
  "-519" : {
    "transaction" : "-519",
    "sampleCount" : 2000,
    "errorCount" : 20,
    "errorPct" : 1.0,
    "meanResTime" : 641.3289999999993,
    "medianResTime" : 449.5,
    "minResTime" : 12.0,
    "maxResTime" : 8835.0,
    "pct1ResTime" : 1334.0,
    "pct2ResTime" : 1650.7999999999993,
    "pct3ResTime" : 3547.51,
    "throughput" : 4.565876465646345,
    "receivedKBytesPerSec" : 1.8198406452040035,
    "sentKBytesPerSec" : 2.1937609581035176
  },
  "-530" : {
    "transaction" : "-530",
    "sampleCount" : 2000,
    "errorCount" : 388,
    "errorPct" : 19.4,
    "meanResTime" : 817.8859999999997,
    "medianResTime" : 684.0,
    "minResTime" : 6.0,
    "maxResTime" : 8906.0,
    "pct1ResTime" : 1421.8000000000002,
    "pct2ResTime" : 1731.7999999999993,
    "pct3ResTime" : 4265.91,
    "throughput" : 4.569475447066054,
    "receivedKBytesPerSec" : 4.989246917603219,
    "sentKBytesPerSec" : 2.9630192352068945
  },
  "-532" : {
    "transaction" : "-532",
    "sampleCount" : 2000,
    "errorCount" : 25,
    "errorPct" : 1.25,
    "meanResTime" : 560.770499999999,
    "medianResTime" : 415.0,
    "minResTime" : 6.0,
    "maxResTime" : 8718.0,
    "pct1ResTime" : 1073.900000000001,
    "pct2ResTime" : 1561.9499999999998,
    "pct3ResTime" : 3264.76,
    "throughput" : 4.570822610945292,
    "receivedKBytesPerSec" : 1.8208523570018147,
    "sentKBytesPerSec" : 2.1961374263526205
  },
  "-531" : {
    "transaction" : "-531",
    "sampleCount" : 2000,
    "errorCount" : 0,
    "errorPct" : 0.0,
    "meanResTime" : 832.0014999999992,
    "medianResTime" : 568.0,
    "minResTime" : 12.0,
    "maxResTime" : 46585.0,
    "pct1ResTime" : 1641.9,
    "pct2ResTime" : 2176.0,
    "pct3ResTime" : 5388.120000000002,
    "throughput" : 4.5702272545502325,
    "receivedKBytesPerSec" : 41.159047121899384,
    "sentKBytesPerSec" : 2.3743758783405506
  },
  "-516" : {
    "transaction" : "-516",
    "sampleCount" : 2000,
    "errorCount" : 0,
    "errorPct" : 0.0,
    "meanResTime" : 13593.123999999989,
    "medianResTime" : 12925.0,
    "minResTime" : 134.0,
    "maxResTime" : 58293.0,
    "pct1ResTime" : 24426.9,
    "pct2ResTime" : 27713.6,
    "pct3ResTime" : 37210.600000000006,
    "throughput" : 4.559506114297699,
    "receivedKBytesPerSec" : 1848.117483671981,
    "sentKBytesPerSec" : 1.950257498107805
  },
  "-538" : {
    "transaction" : "-538",
    "sampleCount" : 2000,
    "errorCount" : 419,
    "errorPct" : 20.95,
    "meanResTime" : 766.3205000000014,
    "medianResTime" : 668.5,
    "minResTime" : 6.0,
    "maxResTime" : 8872.0,
    "pct1ResTime" : 1369.8000000000002,
    "pct2ResTime" : 1661.0,
    "pct3ResTime" : 2881.4200000000014,
    "throughput" : 4.573226502762229,
    "receivedKBytesPerSec" : 4.931114971914673,
    "sentKBytesPerSec" : 2.965451560384883
  },
  "-515" : {
    "transaction" : "-515",
    "sampleCount" : 2000,
    "errorCount" : 0,
    "errorPct" : 0.0,
    "meanResTime" : 674.4340000000025,
    "medianResTime" : 423.0,
    "minResTime" : 7.0,
    "maxResTime" : 17326.0,
    "pct1ResTime" : 1308.0,
    "pct2ResTime" : 1889.6499999999987,
    "pct3ResTime" : 5702.56,
    "throughput" : 4.562220706551121,
    "receivedKBytesPerSec" : 21.43684147195489,
    "sentKBytesPerSec" : 1.9826056781398915
  },
  "-537" : {
    "transaction" : "-537",
    "sampleCount" : 2000,
    "errorCount" : 454,
    "errorPct" : 22.7,
    "meanResTime" : 1716.8224999999989,
    "medianResTime" : 1040.0,
    "minResTime" : 21.0,
    "maxResTime" : 15578.0,
    "pct1ResTime" : 4005.100000000001,
    "pct2ResTime" : 5408.249999999997,
    "pct3ResTime" : 9054.37,
    "throughput" : 4.57253643168402,
    "receivedKBytesPerSec" : 2.3572407686205112,
    "sentKBytesPerSec" : 6.367614210528722
  },
  "-518" : {
    "transaction" : "-518",
    "sampleCount" : 2000,
    "errorCount" : 230,
    "errorPct" : 11.5,
    "meanResTime" : 1167.1409999999976,
    "medianResTime" : 981.5,
    "minResTime" : 115.0,
    "maxResTime" : 8968.0,
    "pct1ResTime" : 2143.9,
    "pct2ResTime" : 2572.7999999999993,
    "pct3ResTime" : 4493.7300000000005,
    "throughput" : 4.564292625928833,
    "receivedKBytesPerSec" : 3.2199658134482316,
    "sentKBytesPerSec" : 2.540670699979917
  },
  "-517" : {
    "transaction" : "-517",
    "sampleCount" : 2000,
    "errorCount" : 0,
    "errorPct" : 0.0,
    "meanResTime" : 1045.9515,
    "medianResTime" : 551.0,
    "minResTime" : 12.0,
    "maxResTime" : 13161.0,
    "pct1ResTime" : 2118.9,
    "pct2ResTime" : 3355.899999999996,
    "pct3ResTime" : 9301.390000000001,
    "throughput" : 4.563480292610356,
    "receivedKBytesPerSec" : 1.8227182028101911,
    "sentKBytesPerSec" : 2.2059792430098892
  },
  "-539" : {
    "transaction" : "-539",
    "sampleCount" : 2000,
    "errorCount" : 402,
    "errorPct" : 20.1,
    "meanResTime" : 735.6489999999999,
    "medianResTime" : 647.5,
    "minResTime" : 12.0,
    "maxResTime" : 7267.0,
    "pct1ResTime" : 1277.7000000000003,
    "pct2ResTime" : 1597.8999999999996,
    "pct3ResTime" : 2514.8500000000004,
    "throughput" : 4.574335234732012,
    "receivedKBytesPerSec" : 4.957527386687999,
    "sentKBytesPerSec" : 2.9661705037715396
  },
  "-534" : {
    "transaction" : "-534",
    "sampleCount" : 2000,
    "errorCount" : 432,
    "errorPct" : 21.6,
    "meanResTime" : 777.7140000000031,
    "medianResTime" : 677.5,
    "minResTime" : 8.0,
    "maxResTime" : 9482.0,
    "pct1ResTime" : 1388.0,
    "pct2ResTime" : 1670.8999999999996,
    "pct3ResTime" : 3243.6400000000003,
    "throughput" : 4.571564412199677,
    "receivedKBytesPerSec" : 4.938528441273683,
    "sentKBytesPerSec" : 2.964373798535728
  },
  "-533" : {
    "transaction" : "-533",
    "sampleCount" : 2000,
    "errorCount" : 31,
    "errorPct" : 1.55,
    "meanResTime" : 554.5070000000005,
    "medianResTime" : 418.0,
    "minResTime" : 8.0,
    "maxResTime" : 8774.0,
    "pct1ResTime" : 1016.6000000000004,
    "pct2ResTime" : 1448.8999999999996,
    "pct3ResTime" : 2759.9300000000003,
    "throughput" : 4.571167361865037,
    "receivedKBytesPerSec" : 1.819837973544369,
    "sentKBytesPerSec" : 2.196303068396092
  },
  "-514" : {
    "transaction" : "-514",
    "sampleCount" : 2000,
    "errorCount" : 0,
    "errorPct" : 0.0,
    "meanResTime" : 941.1184999999989,
    "medianResTime" : 597.0,
    "minResTime" : 17.0,
    "maxResTime" : 19429.0,
    "pct1ResTime" : 1777.9,
    "pct2ResTime" : 2674.5499999999984,
    "pct3ResTime" : 6785.520000000003,
    "throughput" : 4.5588097859410865,
    "receivedKBytesPerSec" : 38.813056530950895,
    "sentKBytesPerSec" : 2.0389989081650564
  },
  "-536" : {
    "transaction" : "-536",
    "sampleCount" : 2000,
    "errorCount" : 36,
    "errorPct" : 1.8,
    "meanResTime" : 559.8144999999997,
    "medianResTime" : 421.0,
    "minResTime" : 6.0,
    "maxResTime" : 8491.0,
    "pct1ResTime" : 1001.0,
    "pct2ResTime" : 1431.699999999999,
    "pct3ResTime" : 3325.940000000001,
    "throughput" : 4.571961531515674,
    "receivedKBytesPerSec" : 1.819194208924926,
    "sentKBytesPerSec" : 2.2547271224759915
  },
  "-535" : {
    "transaction" : "-535",
    "sampleCount" : 2000,
    "errorCount" : 422,
    "errorPct" : 21.1,
    "meanResTime" : 767.1260000000001,
    "medianResTime" : 680.0,
    "minResTime" : 10.0,
    "maxResTime" : 11997.0,
    "pct1ResTime" : 1371.4000000000005,
    "pct2ResTime" : 1646.0,
    "pct3ResTime" : 2568.5400000000004,
    "throughput" : 4.571313635542878,
    "receivedKBytesPerSec" : 4.9512795285432825,
    "sentKBytesPerSec" : 2.9642111855473345
  },
  "-540" : {
    "transaction" : "-540",
    "sampleCount" : 2000,
    "errorCount" : 0,
    "errorPct" : 0.0,
    "meanResTime" : 1756.1309999999992,
    "medianResTime" : 1374.5,
    "minResTime" : 11.0,
    "maxResTime" : 16825.0,
    "pct1ResTime" : 3437.7000000000003,
    "pct2ResTime" : 4639.249999999997,
    "pct3ResTime" : 7416.130000000001,
    "throughput" : 4.5750467798533245,
    "receivedKBytesPerSec" : 122.27566687025625,
    "sentKBytesPerSec" : 2.0641324338791365
  },
  "-521" : {
    "transaction" : "-521",
    "sampleCount" : 2000,
    "errorCount" : 388,
    "errorPct" : 19.4,
    "meanResTime" : 819.425999999999,
    "medianResTime" : 701.5,
    "minResTime" : 12.0,
    "maxResTime" : 9133.0,
    "pct1ResTime" : 1502.6000000000004,
    "pct2ResTime" : 1802.6499999999987,
    "pct3ResTime" : 3265.6500000000005,
    "throughput" : 4.567315377694145,
    "receivedKBytesPerSec" : 4.989872334971477,
    "sentKBytesPerSec" : 2.961618565223547
  },
  "-520" : {
    "transaction" : "-520",
    "sampleCount" : 2000,
    "errorCount" : 374,
    "errorPct" : 18.7,
    "meanResTime" : 849.3674999999998,
    "medianResTime" : 706.5,
    "minResTime" : 13.0,
    "maxResTime" : 11602.0,
    "pct1ResTime" : 1544.0,
    "pct2ResTime" : 1819.749999999999,
    "pct3ResTime" : 4207.77,
    "throughput" : 4.567263227365214,
    "receivedKBytesPerSec" : 5.013626233589252,
    "sentKBytesPerSec" : 2.961584748994631
  },
  "Total" : {
    "transaction" : "Total",
    "sampleCount" : 54000,
    "errorCount" : 4788,
    "errorPct" : 8.866667,
    "meanResTime" : 1377.6658703703736,
    "medianResTime" : 551.0,
    "minResTime" : 6.0,
    "maxResTime" : 58293.0,
    "pct1ResTime" : 2129.800000000003,
    "pct2ResTime" : 4717.950000000001,
    "pct3ResTime" : 23450.94000000001,
    "throughput" : 122.88450904225179,
    "receivedKBytesPerSec" : 2386.3020569323644,
    "sentKBytesPerSec" : 70.34924801507383
  },
  "-527" : {
    "transaction" : "-527",
    "sampleCount" : 2000,
    "errorCount" : 28,
    "errorPct" : 1.4,
    "meanResTime" : 552.2594999999991,
    "medianResTime" : 412.0,
    "minResTime" : 10.0,
    "maxResTime" : 8858.0,
    "pct1ResTime" : 1001.9000000000001,
    "pct2ResTime" : 1429.749999999999,
    "pct3ResTime" : 2492.7700000000004,
    "throughput" : 4.569277094670852,
    "receivedKBytesPerSec" : 1.8196610567367135,
    "sentKBytesPerSec" : 2.195394854080136
  },
  "-526" : {
    "transaction" : "-526",
    "sampleCount" : 2000,
    "errorCount" : 0,
    "errorPct" : 0.0,
    "meanResTime" : 1486.3925000000017,
    "medianResTime" : 1022.0,
    "minResTime" : 14.0,
    "maxResTime" : 32935.0,
    "pct1ResTime" : 2848.0,
    "pct2ResTime" : 4006.5499999999984,
    "pct3ResTime" : 10897.920000000002,
    "throughput" : 4.568734323530352,
    "receivedKBytesPerSec" : 122.1053498736745,
    "sentKBytesPerSec" : 2.0389761580599326
  },
  "-529" : {
    "transaction" : "-529",
    "sampleCount" : 2000,
    "errorCount" : 415,
    "errorPct" : 20.75,
    "meanResTime" : 802.6225000000002,
    "medianResTime" : 686.0,
    "minResTime" : 8.0,
    "maxResTime" : 8919.0,
    "pct1ResTime" : 1401.9,
    "pct2ResTime" : 1657.9499999999998,
    "pct3ResTime" : 3544.460000000003,
    "throughput" : 4.5698408781406235,
    "receivedKBytesPerSec" : 4.956385153043971,
    "sentKBytesPerSec" : 2.9632561944193103
  },
  "-528" : {
    "transaction" : "-528",
    "sampleCount" : 2000,
    "errorCount" : 33,
    "errorPct" : 1.65,
    "meanResTime" : 658.6055000000009,
    "medianResTime" : 452.0,
    "minResTime" : 7.0,
    "maxResTime" : 11695.0,
    "pct1ResTime" : 1277.800000000001,
    "pct2ResTime" : 1722.8999999999996,
    "pct3ResTime" : 4478.87,
    "throughput" : 4.568953504044666,
    "receivedKBytesPerSec" : 1.8185728888008095,
    "sentKBytesPerSec" : 2.1952393788964604
  },
  "-523" : {
    "transaction" : "-523",
    "sampleCount" : 2000,
    "errorCount" : 32,
    "errorPct" : 1.6,
    "meanResTime" : 599.8705000000001,
    "medianResTime" : 425.5,
    "minResTime" : 9.0,
    "maxResTime" : 8774.0,
    "pct1ResTime" : 1150.900000000001,
    "pct2ResTime" : 1573.7999999999956,
    "pct3ResTime" : 3467.130000000001,
    "throughput" : 4.567826513949,
    "receivedKBytesPerSec" : 1.818316127853464,
    "sentKBytesPerSec" : 2.2080801996140185
  },
  "-522" : {
    "transaction" : "-522",
    "sampleCount" : 2000,
    "errorCount" : 401,
    "errorPct" : 20.05,
    "meanResTime" : 840.2849999999992,
    "medianResTime" : 727.5,
    "minResTime" : 10.0,
    "maxResTime" : 8533.0,
    "pct1ResTime" : 1532.5000000000005,
    "pct2ResTime" : 1874.699999999999,
    "pct3ResTime" : 3854.5200000000013,
    "throughput" : 4.567534422081288,
    "receivedKBytesPerSec" : 4.970713004969477,
    "sentKBytesPerSec" : 2.9617606018183356
  },
  "-525" : {
    "transaction" : "-525",
    "sampleCount" : 2000,
    "errorCount" : 0,
    "errorPct" : 0.0,
    "meanResTime" : 1930.8055000000013,
    "medianResTime" : 1414.0,
    "minResTime" : 19.0,
    "maxResTime" : 25516.0,
    "pct1ResTime" : 3790.000000000002,
    "pct2ResTime" : 5139.349999999994,
    "pct3ResTime" : 11254.210000000003,
    "throughput" : 4.56805604091151,
    "receivedKBytesPerSec" : 130.8672865697154,
    "sentKBytesPerSec" : 1.9717585645340698
  },
  "-524" : {
    "transaction" : "-524",
    "sampleCount" : 2000,
    "errorCount" : 258,
    "errorPct" : 12.9,
    "meanResTime" : 749.5034999999998,
    "medianResTime" : 592.0,
    "minResTime" : 11.0,
    "maxResTime" : 8743.0,
    "pct1ResTime" : 1423.6000000000004,
    "pct2ResTime" : 1749.5999999999985,
    "pct3ResTime" : 3816.9,
    "throughput" : 4.5681186431774,
    "receivedKBytesPerSec" : 2.165132099998401,
    "sentKBytesPerSec" : 2.9755225927727795
  }
}